gefyra/__init__.py
gefyra/api/__init__.py
gefyra/api/bridge.py
gefyra/api/clients.py
gefyra/api/connect.py
gefyra/api/install.py
gefyra/api/list.py
gefyra/api/operator.py
gefyra/api/reflect.py
gefyra/api/run.py
gefyra/api/status.py
gefyra/api/utils.py
gefyra/cli/__init__.py
gefyra/cli/bridge.py
gefyra/cli/clients.py
gefyra/cli/connections.py
gefyra/cli/console.py
gefyra/cli/installation.py
gefyra/cli/list.py
gefyra/cli/main.py
gefyra/cli/operator.py
gefyra/cli/run.py
gefyra/cli/self.py
gefyra/cli/status.py
gefyra/cli/telemetry.py
gefyra/cli/updown.py
gefyra/cli/utils.py
gefyra/cli/version.py
gefyra/cluster/__init__.py
gefyra/cluster/resources.py
gefyra/cluster/utils.py
gefyra/configuration.py
gefyra/exceptions.py
gefyra/local/__init__.py
gefyra/local/bridge.py
gefyra/local/cargo.py
gefyra/local/clients.py
gefyra/local/minikube.py
gefyra/local/networking.py
gefyra/local/utils.py
gefyra/misc/__init__.py
gefyra/misc/comps/__init__.py
gefyra/misc/comps/deployment.py
gefyra/misc/comps/namespace.py
gefyra/misc/comps/rbac.py
gefyra/misc/comps/service.py
gefyra/misc/comps/webhook.py
gefyra/misc/install.py
gefyra/misc/uninstall.py
gefyra/misc/utils.py
gefyra/types.py
gefyra-2.3.2.dist-info/METADATA
gefyra-2.3.2.dist-info/WHEEL
gefyra-2.3.2.dist-info/entry_points.txt
gefyra-2.3.2.dist-info/RECORD
