Metadata-Version: 2.3
Name: Gefyra
Version: 2.3.2
Summary: Gefyra runs all developer machine side components of Gefyra's Kubernetes-based development infrastructure
Keywords: Kubernetes,Development,Cloud-native
Author: Michael Schilonka
Author-email: michael@blueshoe.io
Requires-Python: >=3.8.1,<4.0.0
Classifier: Development Status :: 3 - Alpha
Classifier: Intended Audience :: Developers
Classifier: Operating System :: MacOS
Classifier: Operating System :: POSIX :: Linux
Classifier: Programming Language :: Python :: 3
Classifier: Programming Language :: Python :: 3.9
Classifier: Programming Language :: Python :: 3.10
Classifier: Programming Language :: Python :: 3.11
Classifier: Programming Language :: Python :: 3.12
Classifier: Programming Language :: Python :: 3.13
Classifier: Topic :: Software Development :: Build Tools
Requires-Dist: docker (>=6,<8)
Requires-Dist: kubernetes (>=24.2,<33.0)
Project-URL: Documentation, https://gefyra.dev
Project-URL: Homepage, https://gefyra.dev
Project-URL: Repository, https://github.com/gefyrahq/gefyra
Project-URL: issues, https://github.com/gefyrahq/gefyra/issues
